<?xml version="1.0" encoding="UTF-8"?>
<!DOCTYPE mapper PUBLIC "-//mybatis.org//DTD Mapper 3.0//EN" "http://mybatis.org/dtd/mybatis-3-mapper.dtd">
<mapper namespace="com.easy.cloud.core.jdbc.user.dao.UserDAO">
    <!-- 根节点 -->
    <!-- 设置resultMap -->
    <resultMap id="UserEntity" type="com.easy.cloud.core.jdbc.user.entity.UserEntity">
        <id column="id" jdbcType="BIGINT" property="id" />
        <result column="update_date" jdbcType="TIMESTAMP" property="updateDate" />
        <result column="create_by" jdbcType="VARCHAR" property="createBy" />
        <result column="create_date" jdbcType="TIMESTAMP" property="createDate" />
        <result column="update_by" jdbcType="VARCHAR" property="updateBy" />
        <result column="version" jdbcType="INTEGER" property="version" />
        <result column="is_deleted" jdbcType="INTEGER" property="isDeleted" />
        <result column="user_name" jdbcType="VARCHAR" property="userName" />
        <result column="nick_name" jdbcType="VARCHAR" property="nickName" />
        <result column="name" jdbcType="VARCHAR" property="name" />
        <result column="email" jdbcType="VARCHAR" property="email" />
        <result column="phone_number" jdbcType="VARCHAR" property="phoneNumber" />
        <result column="wechat_number" jdbcType="VARCHAR" property="wechatNumber" />
        <result column="user_type" jdbcType="VARCHAR" property="userType" />
        <result column="head_img" jdbcType="VARCHAR" property="headImg" />
        <result column="open_id" jdbcType="VARCHAR" property="openId" />
        <result column="password" jdbcType="CHAR" property="password" />
        <result column="sex" jdbcType="INTEGER" property="sex" />
        <result column="is_frozen" jdbcType="INTEGER" property="isFrozen" />
        <result column="is_manager" jdbcType="INTEGER" property="isManager" />
        <result column="is_subscribe" jdbcType="INTEGER" property="isSubscribe" />
    </resultMap>
    <!-- 设置columnList -->
    <sql id="columnList">eui.id,eui.update_date,eui.create_by,eui.create_date,eui.update_by,eui.version,eui.is_deleted,eui.user_name,eui.nick_name,eui.name,eui.email,eui.phone_number,eui.wechat_number,eui.user_type,eui.head_img,eui.open_id,eui.password,eui.sex,eui.is_frozen,eui.is_manager,eui.is_subscribe</sql>
    <!-- 根据id获取对象信息 -->
    <select id="findById" resultMap="UserEntity" parameterType="java.lang.Long">
        SELECT
        <include refid="columnList" />
        FROM easy_user_info eui 
		WHERE eui.id = #{id, jdbcType=BIGINT}
    </select>
    <!-- 统计列表数量 -->
    <select id="listCount" resultType="java.lang.Integer" parameterType="map">SELECT count(*)
		FROM easy_user_info eui</select>
    <!-- 获取列表分页信息 -->
    <select id="listPage" resultMap="UserEntity" parameterType="map">
        SELECT
        <include refid="columnList" />
        FROM easy_user_info eui 
		LIMIT #{maps.start},#{maps.pageSize}
    </select>
    <!-- 设置column -->
    <sql id="setColumnSql">
        <set>
            <if test="id != null">id = #{id, jdbcType=BIGINT},</if>
            <if test="updateDate != null">update_date = #{updateDate, jdbcType=TIMESTAMP},</if>
            <if test="createBy != null">create_by = #{createBy, jdbcType=VARCHAR},</if>
            <if test="createDate != null">create_date = #{createDate, jdbcType=TIMESTAMP},</if>
            <if test="updateBy != null">update_by = #{updateBy, jdbcType=VARCHAR},</if>
            <if test="version != null">version = #{version, jdbcType=INTEGER},</if>
            <if test="isDeleted != null">is_deleted = #{isDeleted, jdbcType=INTEGER},</if>
            <if test="userName != null">user_name = #{userName, jdbcType=VARCHAR},</if>
            <if test="nickName != null">nick_name = #{nickName, jdbcType=VARCHAR},</if>
            <if test="name != null">name = #{name, jdbcType=VARCHAR},</if>
            <if test="email != null">email = #{email, jdbcType=VARCHAR},</if>
            <if test="phoneNumber != null">phone_number = #{phoneNumber, jdbcType=VARCHAR},</if>
            <if test="wechatNumber != null">wechat_number = #{wechatNumber, jdbcType=VARCHAR},</if>
            <if test="userType != null">user_type = #{userType, jdbcType=VARCHAR},</if>
            <if test="headImg != null">head_img = #{headImg, jdbcType=VARCHAR},</if>
            <if test="openId != null">open_id = #{openId, jdbcType=VARCHAR},</if>
            <if test="password != null">password = #{password, jdbcType=CHAR},</if>
            <if test="sex != null">sex = #{sex, jdbcType=INTEGER},</if>
            <if test="isFrozen != null">is_frozen = #{isFrozen, jdbcType=INTEGER},</if>
            <if test="isManager != null">is_manager = #{isManager, jdbcType=INTEGER},</if>
            <if test="isSubscribe != null">is_subscribe = #{isSubscribe, jdbcType=INTEGER},</if>
        </set>
    </sql>
    <!-- 保存对象 -->
    <insert id="save" useGeneratedKeys="true" parameterType="com.easy.cloud.core.jdbc.user.entity.UserEntity">
        INSERT INTO easy_user_info
        <include refid="setColumnSql" />
    </insert>
    <!-- 更新对象 -->
    <update id="update" parameterType="com.easy.cloud.core.jdbc.user.entity.UserEntity">
        UPDATE easy_user_info
        <include refid="setColumnSql" />
        WHERE eui.id = #{id, jdbcType=BIGINT}
    </update>
</mapper>
